nimrod/__init__.py
nimrod/_modidx.py
nimrod/core.py
nimrod/models.py
nimrod/modules.py
nimrod/utils.py
nimrod/audio/__init__.py
nimrod/audio/datasets.py
nimrod/audio/embedding.py
nimrod/audio/features.py
nimrod/audio/utils.py
nimrod/audio/datasets/__init__.py
nimrod/audio/datasets/stt.py
nimrod/audio/datasets/tts.py
nimrod/data/__init__.py
nimrod/data/utils/__init__.py
nimrod/data/utils/lhotse.py
nimrod/image/__init__.py
nimrod/image/blip.py
nimrod/image/clip.py
nimrod/image/datasets.py
nimrod/image/med.py
nimrod/image/vit.py
nimrod/lm/__init__.py
nimrod/lm/tokenizer.py
nimrod/models/__init__.py
nimrod/models/aligners.py
nimrod/models/autoencoders.py
nimrod/models/conv.py
nimrod/models/lm.py
nimrod/models/mlp.py
nimrod/models/ngram.py
nimrod/models/transformer.py
nimrod/text/__init__.py
nimrod/text/datasets.py
nimrod/text/embeddings.py
nimrod/text/normalizers.py
nimrod/text/phonemizers.py
nimrod/text/tokenizers.py
nimrod/text/utils.py
nimrod/text/models/__init__.py
nimrod/text/models/transformer.py
nimrod/text/models/transformer/__init__.py
nimrod/text/models/transformer/classification.py
nimrod/text/models/transformer/generation.py
nimrod/tts/__init__.py
nimrod/tts/datasets/__init__.py
nimrod/tts/datasets/lhotse.py
nimrod/tts/models/__init__.py
nimrod/tts/models/tacotron2.py
nimrod/tts/models/valle.py
slg_nimrod-0.0.11.dist-info/LICENSE
slg_nimrod-0.0.11.dist-info/METADATA
slg_nimrod-0.0.11.dist-info/WHEEL
slg_nimrod-0.0.11.dist-info/entry_points.txt
slg_nimrod-0.0.11.dist-info/top_level.txt
slg_nimrod-0.0.11.dist-info/RECORD
