Metadata-Version: 2.1
Name: slg-nimrod
Version: 0.0.11
Summary: minimal deep learning framework
Home-page: https://github.com/slegroux/nimrod
Author: Sylvain Le Groux
Author-email: slegroux@ccrma.stanford.edu
License: Apache Software License 2.0
Keywords: nbdev jupyter notebook python
Classifier: Development Status :: 4 - Beta
Classifier: Intended Audience :: Developers
Classifier: Natural Language :: English
Classifier: Programming Language :: Python :: 3.9
Classifier: Programming Language :: Python :: 3.10
Classifier: License :: OSI Approved :: Apache Software License
Requires-Python: >=3.9
License-File: LICENSE
Requires-Dist: torchtext
Requires-Dist: torchvision
Requires-Dist: torchaudio
Requires-Dist: torchdata
Requires-Dist: jupyterlab
Requires-Dist: nbdev
Requires-Dist: numpy
Requires-Dist: lightning
Requires-Dist: anyascii
Requires-Dist: datasets
Requires-Dist: encodec
Requires-Dist: fairscale
Requires-Dist: hydra-colorlog
Requires-Dist: hydra-core
Requires-Dist: hydra-optuna-sweeper
Requires-Dist: inflect
Requires-Dist: ipykernel
Requires-Dist: jupyterlab-quarto
Requires-Dist: librosa
Requires-Dist: lhotse
Requires-Dist: matplotlib
Requires-Dist: nvitop
Requires-Dist: omegaconf
Requires-Dist: onnxruntime
Requires-Dist: optuna
Requires-Dist: pandas
Requires-Dist: phonemizer
Requires-Dist: plum-dispatch
Requires-Dist: portalocker
Requires-Dist: pre-commit
Requires-Dist: python-dotenv
Requires-Dist: pytest
Requires-Dist: spacy ==3.6
Requires-Dist: streamlit
Requires-Dist: timm
Requires-Dist: tensorboard
Requires-Dist: tqdm
Requires-Dist: transformers
Requires-Dist: wandb
Provides-Extra: dev
